yabul/__init__.py
yabul/align.py
yabul/fasta.py
yabul-0.0.3.dist-info/LICENSE
yabul-0.0.3.dist-info/METADATA
yabul-0.0.3.dist-info/WHEEL
yabul-0.0.3.dist-info/top_level.txt
yabul-0.0.3.dist-info/RECORD
