Metadata-Version: 2.1
Name: yabul
Version: 0.0.3
Summary: Yet Another Bioinformatics Utilities Library
Home-page: https://github.com/timodonnell/yabul
Author: Tim O'Donnell
Author-email: timodonnell@gmail.com
License: UNKNOWN
Project-URL: Bug Tracker, https://github.com/timodonnell/yabul/issues
Platform: UNKNOWN
Classifier: Programming Language :: Python :: 3
Classifier: Topic :: Scientific/Engineering :: Bio-Informatics
Classifier: License :: OSI Approved :: MIT License
Classifier: Operating System :: OS Independent
Requires-Python: >=2.7
Requires-Dist: pandas
Requires-Dist: parasail
Requires-Dist: six
